<movieclip version="2.2.0">
	<layer name="Layer 1">
		<frame duration="4">
			<shape>
				<fills>
					<fill type="radial" colors="#A4D9FF,#043EFF" ratios="0,1" cx="-179.05" cy="30" r="8" />
				</fills>
				<figure>
					<polygon fillIndex="0">
						<contour edges="M-183.6,41.9L-175.65,42L-176.85,18.15L-182.1,18.15L-183.6,41.9" />
					</polygon>
				</figure>
			</shape>
		</frame>
		<frame duration="5">
			<shape>
				<fills>
					<fill type="radial" colors="#A4D9FF,#043EFF" ratios="0,1" cx="-178.15" cy="29.75" r="8.25" />
				</fills>
				<figure>
					<polygon fillIndex="0">
						<contour edges="M-183.6,41.9L-174.5,41.9C-173.63,30.03,-176.85,18.15L-182.1,18.15C-180.7,30.03,-183.6,41.9" />
					</polygon>
				</figure>
			</shape>
		</frame>
		<frame duration="5">
			<shape>
				<fills>
					<fill type="radial" colors="#A4D9FF,#043EFF" ratios="0,1" cx="-180.55" cy="30" r="8.21631513074404" />
				</fills>
				<figure>
					<polygon fillIndex="0">
						<contour edges="M-176.2,42.3C-179.33,30.81,-177.65,18.2L-181.8,18.03C-182.4,29.94,-184.4,41.55L-176.2,42.3" />
					</polygon>
				</figure>
			</shape>
		</frame>
		<frame duration="5">
			<shape>
				<fills>
					<fill type="radial" colors="#A4D9FF,#043EFF" ratios="0,1" cx="-180.9" cy="29.5" r="8.30403040494317" />
				</fills>
				<figure>
					<polygon fillIndex="0">
						<contour edges="M-185.27,41.55L-177.05,42.3C-179.73,30.02,-176.57,18.45L-181.8,18.03C-185.84,29.51,-185.27,41.55" />
					</polygon>
				</figure>
			</shape>
		</frame>
		<frame duration="5">
			<shape>
				<fills>
					<fill type="radial" colors="#A4D9FF,#043EFF" ratios="0,1" cx="-180.55" cy="29.85" r="8.49191994168902" />
				</fills>
				<figure>
					<polygon fillIndex="0">
						<contour edges="M-185.27,41.55L-177.35,42.3C-179.33,30.81,-177.65,18.2L-181.8,18.03C-182.4,29.94,-185.27,41.55" />
					</polygon>
				</figure>
			</shape>
		</frame>
		<frame duration="5">
			<shape>
				<fills>
					<fill type="radial" colors="#A4D9FF,#043EFF" ratios="0,1" cx="-178.4" cy="30" r="8.6209048501948" />
				</fills>
				<figure>
					<polygon fillIndex="0">
						<contour edges="M-183.6,41.9L-175.1,41.9C-173.63,30.03,-176.85,18.15L-182.1,18.15C-180.7,30.03,-183.6,41.9" />
					</polygon>
				</figure>
			</shape>
		</frame>
		<frame>
			<shape>
				<fills>
					<fill type="radial" colors="#A4D9FF,#043EFF" ratios="0,1" cx="-179.05" cy="30" r="8" />
				</fills>
				<figure>
					<polygon fillIndex="0">
						<contour edges="M-183.6,41.9L-175.65,42L-176.85,18.15L-182.1,18.15L-183.6,41.9" />
					</polygon>
				</figure>
			</shape>
		</frame>
	</layer>
</movieclip>